scaldys.py
scaldys/__about__.py
scaldys/__init__.py
scaldys/__main__.py
scaldys/cli/__init__.py
scaldys/cli/cli.py
scaldys/cli/settings.py
scaldys/cli/commands/__init__.py
scaldys/cli/commands/arg_types.py
scaldys/cli/commands/cmd_export.py
scaldys/cli/commands/cmd_settings.py
scaldys/common/__init__.py
scaldys/common/app_location.py
scaldys/common/logging.py
scaldys/core/export.py
scaldys-0.1.5.dist-info/METADATA
scaldys-0.1.5.dist-info/WHEEL
scaldys-0.1.5.dist-info/top_level.txt
scaldys-0.1.5.dist-info/RECORD
