Metadata-Version: 2.4
Name: scaldys
Version: 0.1.5
Summary: A skeleton for Python projects by Scaldys.
Author-email: scaldys <scaldys@scaldys.net>
License: MIT License
Classifier: Programming Language :: Python
Classifier: Operating System :: OS Independent
Classifier: Development Status :: 3 - Alpha
Classifier: Intended Audience :: Developers
Classifier: Topic :: Utilities
Requires-Python: >=3.12
Requires-Dist: platformdirs>=4.3.6
Requires-Dist: typer>=0.15.1
